tags/__init__.py
tags/tag.py
tags.py-0.8.7.dist-info/LICENSE
tags.py-0.8.7.dist-info/METADATA
tags.py-0.8.7.dist-info/WHEEL
tags.py-0.8.7.dist-info/top_level.txt
tags.py-0.8.7.dist-info/RECORD
