Metadata-Version: 2.1
Name: tags.py
Version: 0.8.7
Summary: A Tag helper.
Home-page: https://github.com/proguy914629bot/tags.py
Author: priguy914629
License: MIT
Platform: UNKNOWN
Requires-Python: >=3.5
